guardrails_sdk/__init__.py
guardrails_sdk/guardrails.py
guardrails_sdk/compitator_banned_words/__init__.py
guardrails_sdk/compitator_banned_words/block_words.py
guardrails_sdk/log_guardrails/__init__.py
guardrails_sdk/log_guardrails/log_anomaly.py
guardrails_sdk/pii/__init__.py
guardrails_sdk/pii/custom_entity.py
guardrails_sdk/pii/pii.py
guardrails_sdk/prompt_secure/__init__.py
guardrails_sdk/prompt_secure/prompt_break.py
guardrails_sdk/toxicity/__init__.py
guardrails_sdk/toxicity/toxic_bert.py
guardrails_sdk-0.2.1.dist-info/licenses/LICENSE
guardrails_sdk-0.2.1.dist-info/METADATA
guardrails_sdk-0.2.1.dist-info/WHEEL
guardrails_sdk-0.2.1.dist-info/top_level.txt
guardrails_sdk-0.2.1.dist-info/RECORD
